singleton_pattern_decorator/decorator.py
singleton_pattern_decorator-1.0.5.dist-info/LICENSE
singleton_pattern_decorator-1.0.5.dist-info/METADATA
singleton_pattern_decorator-1.0.5.dist-info/WHEEL
singleton_pattern_decorator-1.0.5.dist-info/top_level.txt
singleton_pattern_decorator-1.0.5.dist-info/RECORD
