Metadata-Version: 2.1
Name: singleton-pattern-decorator
Version: 1.0.5
Summary: Singleton decorator
Home-page: https://github.com/jbw/singleton-pattern-decorator
Author: Jason Watson
Author-email: jbw@jbw.cc
License: UNKNOWN
Platform: UNKNOWN
Classifier: License :: OSI Approved :: MIT License
Classifier: Programming Language :: Python :: 3.5
Classifier: Programming Language :: Python :: 3.6
Classifier: Programming Language :: Python :: 3.7
Classifier: Operating System :: OS Independent
